Metadata-Version: 2.2
Name: django-crud-kit
Version: 0.1
Summary: A reusable CRUD system for Django projects
Home-page: https://github.com/Koded0214h/DjangoCrudKit
Author: Koded
Author-email: your-email@example.com
Classifier: Framework :: Django
Classifier: Programming Language :: Python :: 3
Classifier: License :: OSI Approved :: MIT License
Classifier: Operating System :: OS Independent
Requires-Python: >=3.6
Requires-Dist: django>=4.0
Dynamic: author
Dynamic: author-email
Dynamic: classifier
Dynamic: description
Dynamic: description-content-type
Dynamic: home-page
Dynamic: requires-dist
Dynamic: requires-python
Dynamic: summary
